{
  "Workflows": [
    {
      "Path": null,
      "SortBy": 0,
      "VariablesSectionElementsOrder": null,
      "ArgumentsSectionElementsOrder": null,
      "ConstantsSectionElementsOrder": null,
      "AddedNamespaces": null
    },
    {
      "Path": "Main.xaml",
      "SortBy": 0,
      "VariablesSectionElementsOrder": null,
      "ArgumentsSectionElementsOrder": null,
      "ConstantsSectionElementsOrder": null,
      "AddedNamespaces": null
    },
    {
      "Path": "IMDB Open Website.xaml",
      "SortBy": 0,
      "VariablesSectionElementsOrder": null,
      "ArgumentsSectionElementsOrder": [
        "out_browser1",
        "out_bool_imdblogo"
      ],
      "ConstantsSectionElementsOrder": null,
      "AddedNamespaces": null
    }
  ]
}